cool_bayesian_networks/__init__.py
cool_bayesian_networks/bayesian_construct.py
cool_bayesian_networks/main.py
cool_bayesian_networks/test.py
cool_bayesian_networks/version.py
cool_bayesian_networks-0.0.2.dist-info/METADATA
cool_bayesian_networks-0.0.2.dist-info/WHEEL
cool_bayesian_networks-0.0.2.dist-info/LICENSE
cool_bayesian_networks-0.0.2.dist-info/RECORD
