Metadata-Version: 2.1
Name: cool-bayesian-networks
Version: 0.0.2
Summary: This package serves as a Bayesian Network builder
License: MIT
Author: Pedro Arriola
Requires-Python: >=3.8,<4.0
Classifier: License :: OSI Approved :: MIT License
Classifier: Programming Language :: Python :: 3
Classifier: Programming Language :: Python :: 3.8
Classifier: Programming Language :: Python :: 3.9
Classifier: Programming Language :: Python :: 3.10
Classifier: Programming Language :: Python :: 3.11
Requires-Dist: pgmpy (>=0.1.21,<0.2.0)
